main.py
setup.py
OHTA.egg-info/PKG-INFO
OHTA.egg-info/SOURCES.txt
OHTA.egg-info/dependency_links.txt
OHTA.egg-info/requires.txt
OHTA.egg-info/top_level.txt